openquiz_export/__main__.py
openquiz_export/version.py
openquiz_export-0.0.3.dist-info/licenses/LICENSE.md
openquiz_export-0.0.3.dist-info/METADATA
openquiz_export-0.0.3.dist-info/WHEEL
openquiz_export-0.0.3.dist-info/entry_points.txt
openquiz_export-0.0.3.dist-info/top_level.txt
openquiz_export-0.0.3.dist-info/RECORD
