Metadata-Version: 2.4
Name: openquiz_export
Version: 0.0.3
Summary: Openquiz-export exports quiz results from open-quiz.com to Excel
Home-page: https://gitlab.com/peczony/openquiz-export
Author: Alexander Pecheny
Author-email: ap@pecheny.me
Classifier: Programming Language :: Python :: 3
Classifier: License :: OSI Approved :: MIT License
Classifier: Operating System :: OS Independent
License-File: LICENSE.md
Requires-Dist: requests
Requires-Dist: openpyxl
Requires-Dist: levenshtein
Dynamic: author
Dynamic: author-email
Dynamic: classifier
Dynamic: description
Dynamic: description-content-type
Dynamic: home-page
Dynamic: license-file
Dynamic: requires-dist
Dynamic: summary
